CHANGELOG.rst
LICENSE.md
README.rst
acknowledgements.md
cursesmenu/__init__.py
cursesmenu/curses_menu.py
cursesmenu/item_group.py
cursesmenu/items/__init__.py
cursesmenu/items/command_item.py
cursesmenu/items/exit_item.py
cursesmenu/items/external_item.py
cursesmenu/items/function_item.py
cursesmenu/items/menu_item.py
cursesmenu/items/selection_item.py
cursesmenu/items/submenu_item.py
cursesmenu/old_curses_menu.py
cursesmenu/utils.py
docs/Makefile
docs/source/conf.py
docs/source/cursesmenu/CursesMenu.rst
docs/source/cursesmenu/ItemGroup.rst
docs/source/cursesmenu/functions.rst
docs/source/cursesmenu/items/CommandItem.rst
docs/source/cursesmenu/items/ExitItem.rst
docs/source/cursesmenu/items/ExternalItem.rst
docs/source/cursesmenu/items/FunctionItem.rst
docs/source/cursesmenu/items/MenuItem.rst
docs/source/cursesmenu/items/SubmenuItem.rst
docs/source/cursesmenu.rst
docs/source/index.rst
docs/source/installation.rst
docs/source/items.rst
docs/source/usage.rst
test/__init__.py
test/conftest.py
test/example_menus/__init__.py
test/example_menus/basic_menu.py
test/example_menus/menu_with_items.py
test/example_menus/menu_with_lots_of_items.py
test/example_menus/zero_padded_menu_with_lots_of_items.py
test/test_clear.py
test/test_command_item.py
test/test_curses_menu.py
test/test_example_menus.py
test/test_exit_item.py
test/test_external_item.py
test/test_function_item.py
test/test_graphics.py
test/test_item_group.py
test/test_menu_item.py
test/test_selection_item.py
test/test_selection_menu.py
test/test_submenu_item.py
tox.ini
curses_menu-0.8.3.dist-info/LICENSE.md
curses_menu-0.8.3.dist-info/METADATA
curses_menu-0.8.3.dist-info/WHEEL
curses_menu-0.8.3.dist-info/RECORD
