Metadata-Version: 2.1
Name: curses-menu
Version: 0.8.3
Summary: A simple console menu system using curses
Home-page: http://github.com/pmbarrett314/curses-menu
License: MIT
Author: Paul Barrett
Author-email: pmbarrett314@gmail.com
Requires-Python: >=3.8,<4.0
Classifier: Development Status :: 3 - Alpha
Classifier: Environment :: Console
Classifier: Environment :: Console :: Curses
Classifier: Intended Audience :: Developers
Classifier: License :: OSI Approved :: MIT License
Classifier: Operating System :: OS Independent
Classifier: Programming Language :: Python
Classifier: Programming Language :: Python :: 3
Classifier: Programming Language :: Python :: 3.8
Classifier: Programming Language :: Python :: 3.9
Classifier: Programming Language :: Python :: 3.10
Classifier: Programming Language :: Python :: 3.11
Classifier: Programming Language :: Python :: 3.12
Classifier: Programming Language :: Python :: 3 :: Only
Classifier: Programming Language :: Python :: Implementation :: CPython
Classifier: Programming Language :: Python :: Implementation :: PyPy
Classifier: Topic :: Software Development :: Libraries :: Python Modules
Classifier: Typing :: Typed
Requires-Dist: Deprecated (>=1.2.13,<2.0.0)
Requires-Dist: windows-curses (>=2.3.2,<3.0.0) ; sys_platform == "win32"
Project-URL: Repository, http://github.com/pmbarrett314/curses-menu
